gears/__init__.py
gears/example.py
gears/mixins.py
gears/settings.py
gears/admin/__init__.py
gears/admin/singleton.py
gears/decorators/__init__.py
gears/decorators/helper.py
gears/exceptions/__init__.py
gears/exceptions/views.py
gears/management/__init__.py
gears/management/commands/__init__.py
gears/management/commands/run_gears_server.py
gears/models/__init__.py
gears/models/change.py
gears/models/jwt.py
gears/models/singleton.py
gears/pagination/__init__.py
gears/pagination/summary.py
gears/renderers/__init__.py
gears/renderers/exception_handlers.py
gears/renderers/mapping.py
gears/renderers/renderer.py
gears/renderers/types.py
gears/serializers/__init__.py
gears/serializers/jwt.py
gears/views/__init__.py
gears/views/jwt.py
gears/viewsets/__init__.py
gears/viewsets/permissions.py
gears/viewsets/querysets.py
gears/viewsets/serializers.py
gears/viewsets/service_data.py
drf_gears-0.10.6.dist-info/LICENSE
drf_gears-0.10.6.dist-info/METADATA
drf_gears-0.10.6.dist-info/WHEEL
drf_gears-0.10.6.dist-info/top_level.txt
drf_gears-0.10.6.dist-info/RECORD
