Metadata-Version: 2.1
Name: drf-gears
Version: 0.10.6
Summary: Some gears collection for getting life a little bit better.
Home-page: https://github.com/san4ezy/drf-gears
Author: Alexander Yudkin
Author-email: san4ezy@gmail.com
Classifier: Environment :: Web Environment
Classifier: Framework :: Django
Classifier: Intended Audience :: Developers
Classifier: Operating System :: OS Independent
Classifier: Programming Language :: Python
Classifier: Topic :: Software Development :: Libraries :: Python Modules
Requires-Python: >=3.7
License-File: LICENSE
